edgeprotecttools/__about__.py
edgeprotecttools/__init__.py
edgeprotecttools/__main__.py
edgeprotecttools/api_common.py
edgeprotecttools/api_cyw559xx.py
edgeprotecttools/api_mxs22.py
edgeprotecttools/api_mxs40sv2.py
edgeprotecttools/api_mxs40v1.py
edgeprotecttools/api_traveo_t2g.py
edgeprotecttools/cli.py
edgeprotecttools/cli_creator.py
edgeprotecttools/cli_cyw559xx.py
edgeprotecttools/cli_mxs22.py
edgeprotecttools/cli_mxs40sv2.py
edgeprotecttools/cli_mxs40v1.py
edgeprotecttools/cli_pse8x.py
edgeprotecttools/cli_psoc_c3.py
edgeprotecttools/cli_traveo_t2g.py
edgeprotecttools/main.py
edgeprotecttools/pkg_globals.py
edgeprotecttools/pyinstaller_wrapper.py
edgeprotecttools/core/__init__.py
edgeprotecttools/core/bitops.py
edgeprotecttools/core/connect_helper.py
edgeprotecttools/core/cose.py
edgeprotecttools/core/crc.py
edgeprotecttools/core/cy_bootloader_map_parser.py
edgeprotecttools/core/dependecy_validator.py
edgeprotecttools/core/deprecated.py
edgeprotecttools/core/entrance_exam_base.py
edgeprotecttools/core/enums.py
edgeprotecttools/core/exceptions.py
edgeprotecttools/core/json_helper.py
edgeprotecttools/core/json_validator.py
edgeprotecttools/core/jsonpath.py
edgeprotecttools/core/key_data.py
edgeprotecttools/core/key_helper.py
edgeprotecttools/core/key_validator.py
edgeprotecttools/core/logging_configurator.py
edgeprotecttools/core/logging_formatter.py
edgeprotecttools/core/memory_area.py
edgeprotecttools/core/memory_map_base.py
edgeprotecttools/core/mtb_tools_discovery.py
edgeprotecttools/core/ocd_settings.py
edgeprotecttools/core/policy_filter_base.py
edgeprotecttools/core/policy_parser_base.py
edgeprotecttools/core/policy_validator_base.py
edgeprotecttools/core/progress_bar.py
edgeprotecttools/core/project_base.py
edgeprotecttools/core/ram_app_loader_base.py
edgeprotecttools/core/register_map_base.py
edgeprotecttools/core/signtool_base.py
edgeprotecttools/core/status_codes_base.py
edgeprotecttools/core/strops.py
edgeprotecttools/core/target_builder.py
edgeprotecttools-1.6.1.dist-info/licenses/LICENSE
edgeprotecttools-1.6.1.dist-info/METADATA
edgeprotecttools-1.6.1.dist-info/WHEEL
edgeprotecttools-1.6.1.dist-info/entry_points.txt
edgeprotecttools-1.6.1.dist-info/top_level.txt
edgeprotecttools-1.6.1.dist-info/RECORD
