Metadata-Version: 2.4
Name: edgeprotecttools
Version: 1.6.1
Summary: Python tools for provisioning Cypress/Infineon MCUs
Home-page: https://github.com/Infineon/edgeprotecttools
Author: Cypress Semiconductor Corporation (an Infineon company)
License: Apache 2.0
Classifier: License :: OSI Approved :: Apache Software License
Classifier: Programming Language :: Python :: 3.9
Classifier: Programming Language :: Python :: 3.10
Classifier: Programming Language :: Python :: 3.11
Classifier: Programming Language :: Python :: 3.12
Classifier: Programming Language :: Python :: 3.13
Classifier: Operating System :: OS Independent
Classifier: Topic :: Software Development :: Embedded Systems
Requires-Python: >=3.9
License-File: LICENSE
Requires-Dist: setuptools<81.0.0,>=80.9.0
Requires-Dist: cryptography>=44.0.2
Requires-Dist: click>=8.0.4
Requires-Dist: intelhex>=2.3.0
Requires-Dist: python-jose>=3.3.0
Requires-Dist: jsonschema>=4.21.1
Requires-Dist: cbor>=1.0.0
Requires-Dist: cwt>=2.7.5
Requires-Dist: packaging>=24.1
Requires-Dist: pyelftools>=0.31
Requires-Dist: pyserial>=3.5
Requires-Dist: pyhsslms<3.0.0,>=2.0.0
Dynamic: author
Dynamic: classifier
Dynamic: description
Dynamic: description-content-type
Dynamic: home-page
Dynamic: license
Dynamic: license-file
Dynamic: requires-dist
Dynamic: requires-python
Dynamic: summary
